{
  "version": "1.0",
  "last_updated": "2025-10-20T11:03:08.876799",
  "total_records": 20,
  "tasks": [
    {
      "task_id": "SSS000X_20251019_193911",
      "script_id": "SSS000X",
      "start_time": "2025-10-19T19:38:58.668783",
      "end_time": "2025-10-19T19:39:11.659231",
      "duration": 12.990448,
      "status": "interrupted",
      "statistics": {
        "cycle_count": 0,
        "click_count": 0,
        "duration": 12.990448,
        "avg_clicks_per_cycle": 0.0,
        "cycles_per_minute": 0.0,
        "ocr_check_interval": 0.05,
        "ocr_area": "(0.8000,0.8363)-(0.8800,0.8600)",
        "coord_area1": "(0.8250,0.8400)-(0.8650,0.8550)",
        "m3_coord": "(0.8500,0.7000)"
      },
      "summary": "运行时长: 13.0秒 | 循环次数: 0 | 点击次数: 0 | 平均每轮点击: 0.0 | 每分钟循环: 0.0"
    },
    {
      "task_id": "SSS000X_20251019_193926",
      "script_id": "SSS000X",
      "start_time": "2025-10-19T19:39:20.903533",
      "end_time": "2025-10-19T19:39:26.277194",
      "duration": 5.373661,
      "status": "interrupted",
      "statistics": {
        "cycle_count": 0,
        "click_count": 0,
        "duration": 5.373661,
        "avg_clicks_per_cycle": 0.0,
        "cycles_per_minute": 0.0,
        "ocr_check_interval": 0.05,
        "ocr_area": "(0.8000,0.8363)-(0.8800,0.8600)",
        "coord_area1": "(0.8250,0.8400)-(0.8650,0.8550)",
        "m3_coord": "(0.8500,0.7000)"
      },
      "summary": "运行时长: 5.4秒 | 循环次数: 0 | 点击次数: 0 | 平均每轮点击: 0.0 | 每分钟循环: 0.0"
    },
    {
      "task_id": "SSS000X_20251019_194103",
      "script_id": "SSS000X",
      "start_time": "2025-10-19T19:40:58.534861",
      "end_time": "2025-10-19T19:41:03.769865",
      "duration": 5.235004,
      "status": "interrupted",
      "statistics": {
        "cycle_count": 0,
        "click_count": 0,
        "duration": 5.235004,
        "avg_clicks_per_cycle": 0.0,
        "cycles_per_minute": 0.0,
        "ocr_check_interval": 0.05,
        "ocr_area": "(0.8000,0.8363)-(0.8800,0.8600)",
        "coord_area1": "(0.8250,0.8400)-(0.8650,0.8550)",
        "m3_coord": "(0.5800,0.6300)"
      },
      "summary": "运行时长: 5.2秒 | 循环次数: 0 | 点击次数: 0 | 平均每轮点击: 0.0 | 每分钟循环: 0.0"
    },
    {
      "task_id": "SSS000X_20251019_194126",
      "script_id": "SSS000X",
      "start_time": "2025-10-19T19:41:21.160060",
      "end_time": "2025-10-19T19:41:26.730299",
      "duration": 5.570239,
      "status": "interrupted",
      "statistics": {
        "cycle_count": 0,
        "click_count": 0,
        "duration": 5.570239,
        "avg_clicks_per_cycle": 0.0,
        "cycles_per_minute": 0.0,
        "ocr_check_interval": 0.05,
        "ocr_area": "(0.8000,0.8363)-(0.8800,0.8600)",
        "coord_area1": "(0.8250,0.8400)-(0.8650,0.8550)",
        "m3_coord": "(0.5800,0.6300)"
      },
      "summary": "运行时长: 5.6秒 | 循环次数: 0 | 点击次数: 0 | 平均每轮点击: 0.0 | 每分钟循环: 0.0"
    },
    {
      "task_id": "SSS000X_20251019_194631",
      "script_id": "SSS000X",
      "start_time": "2025-10-19T19:46:26.051809",
      "end_time": "2025-10-19T19:46:31.030895",
      "duration": 4.979086,
      "status": "interrupted",
      "statistics": {
        "cycle_count": 0,
        "click_count": 0,
        "duration": 4.979086,
        "avg_clicks_per_cycle": 0.0,
        "cycles_per_minute": 0.0,
        "ocr_check_interval": 0.05,
        "auto_click": 1,
        "ocr_area": "(0.8000,0.8363)-(0.8800,0.8600)",
        "coord_area1": "(0.8250,0.8400)-(0.8650,0.8550)",
        "m3_coord": "(0.5800,0.6300)"
      },
      "summary": "运行时长: 5.0秒 | 循环次数: 0 | 点击次数: 0 | 平均每轮点击: 0.0 | 每分钟循环: 0.0"
    },
    {
      "task_id": "SSS000X_20251019_194651",
      "script_id": "SSS000X",
      "start_time": "2025-10-19T19:46:37.833655",
      "end_time": "2025-10-19T19:46:51.096379",
      "duration": 13.262724,
      "status": "interrupted",
      "statistics": {
        "cycle_count": 0,
        "click_count": 0,
        "duration": 13.262724,
        "avg_clicks_per_cycle": 0.0,
        "cycles_per_minute": 0.0,
        "ocr_check_interval": 0.05,
        "auto_click": 1,
        "ocr_area": "(0.8000,0.8363)-(0.8800,0.8600)",
        "coord_area1": "(0.8250,0.8400)-(0.8650,0.8550)",
        "m3_coord": "(0.5800,0.6300)"
      },
      "summary": "运行时长: 13.3秒 | 循环次数: 0 | 点击次数: 0 | 平均每轮点击: 0.0 | 每分钟循环: 0.0"
    },
    {
      "task_id": "SSS000X_20251019_194712",
      "script_id": "SSS000X",
      "start_time": "2025-10-19T19:47:06.362569",
      "end_time": "2025-10-19T19:47:12.421986",
      "duration": 6.059417,
      "status": "interrupted",
      "statistics": {
        "cycle_count": 0,
        "click_count": 0,
        "duration": 6.059417,
        "avg_clicks_per_cycle": 0.0,
        "cycles_per_minute": 0.0,
        "ocr_check_interval": 0.05,
        "auto_click": 1,
        "ocr_area": "(0.8000,0.8363)-(0.8800,0.8600)",
        "coord_area1": "(0.8250,0.8400)-(0.8650,0.8550)",
        "m3_coord": "(0.5800,0.6300)"
      },
      "summary": "运行时长: 6.1秒 | 循环次数: 0 | 点击次数: 0 | 平均每轮点击: 0.0 | 每分钟循环: 0.0"
    },
    {
      "task_id": "SSS000X_20251019_200305",
      "script_id": "SSS000X",
      "start_time": "2025-10-19T20:02:55.499819",
      "end_time": "2025-10-19T20:03:05.174526",
      "duration": 9.674707,
      "status": "interrupted",
      "statistics": {
        "cycle_count": 0,
        "click_count": 0,
        "duration": 9.674707,
        "avg_clicks_per_cycle": 0.0,
        "cycles_per_minute": 0.0,
        "ocr_check_interval": 0.05,
        "auto_click": 1,
        "ocr_area": "(0.8000,0.8363)-(0.8800,0.8600)",
        "coord_area1": "(0.8250,0.8400)-(0.8650,0.8550)",
        "m3_coord": "(0.5800,0.6300)"
      },
      "summary": "运行时长: 9.7秒 | 循环次数: 0 | 点击次数: 0 | 平均每轮点击: 0.0 | 每分钟循环: 0.0"
    },
    {
      "task_id": "SSS000X_20251019_200324",
      "script_id": "SSS000X",
      "start_time": "2025-10-19T20:03:18.675562",
      "end_time": "2025-10-19T20:03:24.639199",
      "duration": 5.962965,
      "status": "interrupted",
      "statistics": {
        "cycle_count": 0,
        "click_count": 0,
        "duration": 5.962965,
        "avg_clicks_per_cycle": 0.0,
        "cycles_per_minute": 0.0,
        "ocr_check_interval": 0.05,
        "auto_click": 1,
        "ocr_area": "(0.8000,0.8363)-(0.8800,0.8600)",
        "coord_area1": "(0.8250,0.8400)-(0.8650,0.8550)",
        "m3_coord": "(0.5800,0.6300)"
      },
      "summary": "运行时长: 6.0秒 | 循环次数: 0 | 点击次数: 0 | 平均每轮点击: 0.0 | 每分钟循环: 0.0"
    },
    {
      "task_id": "SSS000X_20251019_200649",
      "script_id": "SSS000X",
      "start_time": "2025-10-19T20:06:43.862438",
      "end_time": "2025-10-19T20:06:49.842405",
      "duration": 5.979967,
      "status": "interrupted",
      "statistics": {
        "cycle_count": 0,
        "click_count": 0,
        "duration": 5.979967,
        "avg_clicks_per_cycle": 0.0,
        "cycles_per_minute": 0.0,
        "ocr_check_interval": 0.05,
        "auto_click": 1,
        "ocr_area": "(0.8000,0.8363)-(0.8800,0.8600)",
        "coord_area1": "(0.8250,0.8400)-(0.8650,0.8550)",
        "coord_area2": "(0.6000,0.6500)-(0.6600,0.6600)",
        "m1_coord": "(0.8518,0.8541)",
        "m2_coord": "(0.6387,0.6552)"
      },
      "summary": "运行时长: 6.0秒 | 循环次数: 0 | 点击次数: 0 | 平均每轮点击: 0.0 | 每分钟循环: 0.0"
    },
    {
      "task_id": "SSS000X_20251019_200913",
      "script_id": "SSS000X",
      "start_time": "2025-10-19T20:08:35.704297",
      "end_time": "2025-10-19T20:09:13.169587",
      "duration": 37.46529,
      "status": "interrupted",
      "statistics": {
        "cycle_count": 0,
        "click_count": 0,
        "duration": 37.46529,
        "avg_clicks_per_cycle": 0.0,
        "cycles_per_minute": 0.0,
        "ocr_check_interval": 0.05,
        "auto_click": 1,
        "ocr_area": "(0.8000,0.8363)-(0.8800,0.8600)",
        "coord_area1": "(0.8250,0.8400)-(0.8650,0.8550)",
        "coord_area2": "(0.6000,0.6500)-(0.6600,0.6600)",
        "m1_coord": "(0.8525,0.8414)",
        "m2_coord": "(0.6444,0.6518)"
      },
      "summary": "运行时长: 37.5秒 | 循环次数: 0 | 点击次数: 0 | 平均每轮点击: 0.0 | 每分钟循环: 0.0"
    },
    {
      "task_id": "SSS000X_20251019_201312",
      "script_id": "SSS000X",
      "start_time": "2025-10-19T20:13:06.293608",
      "end_time": "2025-10-19T20:13:12.645274",
      "duration": 6.351666,
      "status": "interrupted",
      "statistics": {
        "cycle_count": 0,
        "click_count": 0,
        "duration": 6.351666,
        "avg_clicks_per_cycle": 0.0,
        "cycles_per_minute": 0.0,
        "ocr_check_interval": 0.05,
        "auto_click": 1,
        "ocr_area": "(0.8000,0.8363)-(0.8800,0.8600)",
        "coord_area1": "(0.8250,0.8400)-(0.8650,0.8550)",
        "coord_area2": "(0.6000,0.6500)-(0.6600,0.6600)",
        "m1_coord": "(0.8318,0.8546)",
        "m2_coord": "(0.6394,0.6534)"
      },
      "summary": "运行时长: 6.4秒 | 循环次数: 0 | 点击次数: 0 | 平均每轮点击: 0.0 | 每分钟循环: 0.0"
    },
    {
      "task_id": "SSS000X_20251019_201325",
      "script_id": "SSS000X",
      "start_time": "2025-10-19T20:13:16.986716",
      "end_time": "2025-10-19T20:13:25.192580",
      "duration": 8.205864,
      "status": "interrupted",
      "statistics": {
        "cycle_count": 0,
        "click_count": 0,
        "duration": 8.205864,
        "avg_clicks_per_cycle": 0.0,
        "cycles_per_minute": 0.0,
        "ocr_check_interval": 0.05,
        "auto_click": 1,
        "ocr_area": "(0.8000,0.8363)-(0.8800,0.8600)",
        "coord_area1": "(0.8250,0.8400)-(0.8650,0.8550)",
        "coord_area2": "(0.6000,0.6500)-(0.6600,0.6600)",
        "m1_coord": "(0.8387,0.8419)",
        "m2_coord": "(0.6298,0.6562)"
      },
      "summary": "运行时长: 8.2秒 | 循环次数: 0 | 点击次数: 0 | 平均每轮点击: 0.0 | 每分钟循环: 0.0"
    },
    {
      "task_id": "SSS000X_20251019_201647",
      "script_id": "SSS000X",
      "start_time": "2025-10-19T20:16:35.750138",
      "end_time": "2025-10-19T20:16:47.827721",
      "duration": 12.077583,
      "status": "interrupted",
      "statistics": {
        "cycle_count": 0,
        "click_count": 0,
        "duration": 12.077583,
        "avg_clicks_per_cycle": 0.0,
        "cycles_per_minute": 0.0,
        "ocr_check_interval": 0.05,
        "auto_click": 1,
        "ocr_area": "(0.8000,0.8363)-(0.8800,0.8600)",
        "coord_area1": "(0.8250,0.8400)-(0.8650,0.8550)",
        "coord_area2": "(0.6000,0.6500)-(0.6600,0.6600)",
        "m1_coord": "(0.8483,0.8412)",
        "m2_coord": "(0.6400,0.6505)",
        "m2_cycle_count": 3
      },
      "summary": "运行时长: 12.1秒 | 循环次数: 0 | 点击次数: 0 | 平均每轮点击: 0.0 | 每分钟循环: 0.0"
    },
    {
      "task_id": "SSS000X_20251019_201809",
      "script_id": "SSS000X",
      "start_time": "2025-10-19T20:17:47.941819",
      "end_time": "2025-10-19T20:18:09.815784",
      "duration": 21.873965,
      "status": "interrupted",
      "statistics": {
        "cycle_count": 0,
        "click_count": 0,
        "duration": 21.873965,
        "avg_clicks_per_cycle": 0.0,
        "cycles_per_minute": 0.0,
        "ocr_check_interval": 0.05,
        "auto_click": 0,
        "ocr_area": "(0.8000,0.8363)-(0.8800,0.8600)",
        "coord_area1": "(0.8250,0.8400)-(0.8650,0.8550)",
        "coord_area2": "(0.6000,0.6500)-(0.6600,0.6600)",
        "m1_coord": "(0.8483,0.8466)",
        "m2_coord": "(0.6308,0.6598)",
        "m2_cycle_count": 3
      },
      "summary": "运行时长: 21.9秒 | 循环次数: 0 | 点击次数: 0 | 平均每轮点击: 0.0 | 每分钟循环: 0.0"
    },
    {
      "task_id": "SSS000X_20251019_201900",
      "script_id": "SSS000X",
      "start_time": "2025-10-19T20:18:54.388071",
      "end_time": "2025-10-19T20:19:00.781007",
      "duration": 6.392936,
      "status": "interrupted",
      "statistics": {
        "cycle_count": 0,
        "click_count": 0,
        "duration": 6.392936,
        "avg_clicks_per_cycle": 0.0,
        "cycles_per_minute": 0.0,
        "ocr_check_interval": 0.05,
        "auto_click": 0,
        "ocr_area": "(0.8000,0.8363)-(0.8800,0.8600)",
        "coord_area1": "(0.8250,0.8400)-(0.8650,0.8550)",
        "coord_area2": "(0.6000,0.6500)-(0.6600,0.6600)",
        "m1_coord": "(0.8312,0.8520)",
        "m2_coord": "(0.6507,0.6585)",
        "m2_cycle_count": 0
      },
      "summary": "运行时长: 6.4秒 | 循环次数: 0 | 点击次数: 0 | 平均每轮点击: 0.0 | 每分钟循环: 0.0"
    },
    {
      "task_id": "SSS000X_20251019_201931",
      "script_id": "SSS000X",
      "start_time": "2025-10-19T20:19:19.372844",
      "end_time": "2025-10-19T20:19:31.398884",
      "duration": 12.02604,
      "status": "interrupted",
      "statistics": {
        "cycle_count": 0,
        "click_count": 0,
        "duration": 12.02604,
        "avg_clicks_per_cycle": 0.0,
        "cycles_per_minute": 0.0,
        "ocr_check_interval": 0.05,
        "auto_click": 1,
        "ocr_area": "(0.8000,0.8363)-(0.8800,0.8600)",
        "coord_area1": "(0.8250,0.8400)-(0.8650,0.8550)",
        "coord_area2": "(0.6000,0.6500)-(0.6600,0.6600)",
        "m1_coord": "(0.8269,0.8410)",
        "m2_coord": "(0.6458,0.6514)",
        "m2_cycle_count": 3
      },
      "summary": "运行时长: 12.0秒 | 循环次数: 0 | 点击次数: 0 | 平均每轮点击: 0.0 | 每分钟循环: 0.0"
    },
    {
      "task_id": "SMB000X_20251020_000129",
      "script_id": "SMB000X",
      "start_time": "2025-10-20T00:01:23.600123",
      "end_time": "2025-10-20T00:01:29.260069",
      "duration": 5.659448,
      "status": "interrupted",
      "statistics": {
        "refresh_count": 0,
        "purchase_count": 0,
        "low_price_found_count": 0,
        "initial_balance": 51577132,
        "final_balance": 51577132,
        "balance_change": 0,
        "balance_change_percentage": 0.0,
        "total_cost": 0,
        "refresh_cost_total": 0,
        "purchase_cost_total": 0,
        "refresh_efficiency": null,
        "target_price": 450,
        "min_price_threshold": 200,
        "work_time_range": "02:00-05:15"
      },
      "summary": "运行时长: 5.7秒 | 刷新次数: 0 | 购买次数: 0 | 发现低价: 0次 | 总花费: 0 | 刷新花费: 0 | 购买花费: 0"
    },
    {
      "task_id": "SMB000X_20251020_000208",
      "script_id": "SMB000X",
      "start_time": "2025-10-20T00:02:01.981023",
      "end_time": "2025-10-20T00:02:08.447992",
      "duration": 6.466969,
      "status": "interrupted",
      "statistics": {
        "refresh_count": 0,
        "purchase_count": 0,
        "low_price_found_count": 0,
        "initial_balance": 51577132,
        "final_balance": 51577132,
        "balance_change": 0,
        "balance_change_percentage": 0.0,
        "total_cost": 0,
        "refresh_cost_total": 0,
        "purchase_cost_total": 0,
        "refresh_efficiency": null,
        "target_price": 450,
        "min_price_threshold": 200,
        "work_time_range": "02:00-05:15"
      },
      "summary": "运行时长: 6.5秒 | 刷新次数: 0 | 购买次数: 0 | 发现低价: 0次 | 总花费: 0 | 刷新花费: 0 | 购买花费: 0"
    },
    {
      "task_id": "SMB000X_20251020_110308",
      "script_id": "SMB000X",
      "start_time": "2025-10-20T00:02:13.213803",
      "end_time": "2025-10-20T11:03:08.875723",
      "duration": 39655.661417,
      "status": "interrupted",
      "statistics": {
        "refresh_count": 1108,
        "purchase_count": 477,
        "low_price_found_count": 159,
        "initial_balance": 51577132,
        "final_balance": 17781564,
        "balance_change": -33795568,
        "balance_change_percentage": -65.52432578065799,
        "total_cost": 33795568,
        "refresh_cost_total": 17863976,
        "purchase_cost_total": -585726830,
        "refresh_efficiency": 14.350180505415164,
        "target_price": 450,
        "min_price_threshold": 200,
        "work_time_range": "02:00-05:15",
        "refresh_cost_stats": {
          "count": 1107,
          "average": 16137.286359530262,
          "mode": 17298,
          "mode_count": 348,
          "max_price": 17608,
          "max_count": 103,
          "min_price": 12028,
          "min_count": 2
        },
        "refresh_unit_stats": {
          "count": 1107,
          "average": 520.5576245009762,
          "mode": 558,
          "mode_count": 348,
          "max_price": 568.0,
          "max_count": 103,
          "min_price": 388.0,
          "min_count": 2
        },
        "purchase_cost_stats": {
          "count": 159,
          "average": -3683816.540880503,
          "mode": 83600,
          "mode_count": 23,
          "max_price": 300113600,
          "max_count": 1,
          "min_price": -299918400,
          "min_count": 1
        },
        "purchase_unit_stats": {
          "count": 159,
          "average": -6139.694234800837,
          "mode": 139,
          "mode_count": 23,
          "max_price": 500189.3333333333,
          "max_count": 1,
          "min_price": -499864.0,
          "min_count": 1
        }
      },
      "summary": "运行时长: 39655.7秒 | 刷新次数: 1108 | 购买次数: 477 | 发现低价: 159次 | 总花费: 33,795,568 | 刷新花费: 17,863,976 | 购买花费: -585,726,830 | 发现效率: 14.4%"
    }
  ]
}